{
    "type": "DrawBlurSpin",
    "parentType": "DrawBlock",
    "fields": [
        {
            "name": "region",
            "type": "TextureRegion",
            "defaultValue": "null",
            "notes": ""
        },
        {
            "name": "blurRegion",
            "type": "TextureRegion",
            "defaultValue": "null",
            "notes": ""
        },
        {
            "name": "suffix",
            "type": "String",
            "defaultValue": "\"\"",
            "notes": ""
        },
        {
            "name": "rotateSpeed",
            "type": "float",
            "defaultValue": "1.0",
            "notes": ""
        },
        {
            "name": "x",
            "type": "float",
            "defaultValue": "0.0",
            "notes": ""
        },
        {
            "name": "y",
            "type": "float",
            "defaultValue": "0.0",
            "notes": ""
        },
        {
            "name": "blurThresh",
            "type": "float",
            "defaultValue": "0.7",
            "notes": ""
        }
    ]
}